doorstop_edit/__init__.py
doorstop_edit/__main__.py
doorstop_edit/app_signals.py
doorstop_edit/application.py
doorstop_edit/build_info.py
doorstop_edit/custom.css
doorstop_edit/dialogs/__init__.py
doorstop_edit/dialogs/confirm_dialog.py
doorstop_edit/dialogs/diff_dialog.py
doorstop_edit/dialogs/differs/__init__.py
doorstop_edit/dialogs/differs/differ.py
doorstop_edit/dialogs/differs/git_differ.py
doorstop_edit/dialogs/differs/simple_differ.py
doorstop_edit/dialogs/info_dialog.py
doorstop_edit/dialogs/setting_dialog.py
doorstop_edit/doorstop_data.py
doorstop_edit/item_edit/item_edit_view.py
doorstop_edit/item_edit/item_picker_dialog.py
doorstop_edit/item_edit/mdformat/__init__.py
doorstop_edit/item_edit/mdformat/plugin.py
doorstop_edit/item_render/__init__.py
doorstop_edit/item_render/fragmented_markdown.py
doorstop_edit/item_render/item_render_view.py
doorstop_edit/item_render/markdown_css.py
doorstop_edit/item_render/render_worker.py
doorstop_edit/item_tree/__init__.py
doorstop_edit/item_tree/document_item_level_tree.py
doorstop_edit/item_tree/item_tree_view.py
doorstop_edit/main.py
doorstop_edit/main_window.py
doorstop_edit/pinned_items/pinned_items_view.py
doorstop_edit/settings.py
doorstop_edit/theme.py
doorstop_edit/ui_gen/__init__.py
doorstop_edit/ui_gen/resources_rc.py
doorstop_edit/ui_gen/ui_confirm_dialog.py
doorstop_edit/ui_gen/ui_diff_dialog.py
doorstop_edit/ui_gen/ui_info_dialog.py
doorstop_edit/ui_gen/ui_item_picker.py
doorstop_edit/ui_gen/ui_item_viewer.py
doorstop_edit/ui_gen/ui_main.py
doorstop_edit/utils/custom_color_item_delegate.py
doorstop_edit/utils/debug_timer.py
doorstop_edit/utils/file_watcher.py
doorstop_edit/utils/item_utils.py
doorstop_edit/utils/spell_checker.py
doorstop_edit/utils/version_summary.py
doorstop_edit-0.1.4.dist-info/LICENSE
doorstop_edit-0.1.4.dist-info/METADATA
doorstop_edit-0.1.4.dist-info/WHEEL
doorstop_edit-0.1.4.dist-info/entry_points.txt
doorstop_edit-0.1.4.dist-info/RECORD
