Metadata-Version: 2.3
Name: doorstop-edit
Version: 0.1.4
Summary: Cross-platform doorstop GUI editor
License: MIT
Keywords: doorstop,requirements-management,documentation,gui
Author: Alexander Ernfridsson
Author-email: <ernfridsson@gmail.com>
Requires-Python: >=3.9,<3.12
Classifier: Operating System :: OS Independent
Classifier: Programming Language :: Python
Classifier: Programming Language :: Python :: 3
Classifier: Programming Language :: Python :: 3.9
Classifier: Programming Language :: Python :: 3.10
Classifier: Programming Language :: Python :: 3.11
Classifier: Topic :: Software Development :: Documentation
Classifier: Topic :: Text Editors :: Documentation
Classifier: Topic :: Text Processing :: Markup
Requires-Dist: PySide6 (>=6.4,<7.0)
Requires-Dist: doorstop (>=3.0.2,<4)
Requires-Dist: markdown (>=3.4,<4.0)
Requires-Dist: mdformat-myst (>=0.1.5,<0.2.0)
Requires-Dist: plantuml-markdown (>=3.8,<4.0)
Requires-Dist: pygments (>=2.14,<3.0)
Requires-Dist: pyspellchecker (>=0.7,<1.0)
Requires-Dist: qt-material (>=2.12,<3.0)
Requires-Dist: setuptools (>=65.0,<66.0)
Requires-Dist: watchdog (>=3.0,<4.0)
Project-URL: GitHub, https://github.com/ownbee/doorstop-edit
Project-URL: Repository, https://github.com/ownbee/doorstop-edit.git
